README.md
setup.py
cleandev_generic_utils.egg-info/PKG-INFO
cleandev_generic_utils.egg-info/SOURCES.txt
cleandev_generic_utils.egg-info/dependency_links.txt
cleandev_generic_utils.egg-info/requires.txt
cleandev_generic_utils.egg-info/top_level.txt
generic_utils/__init__.py
generic_utils/exceptions.py
generic_utils/interfaces.py